AthenaColor/__init__.py
AthenaColor/py.typed
AthenaColor/data/__init__.py
AthenaColor/data/colors_html.py
AthenaColor/data/style.py
AthenaColor/func/__init__.py
AthenaColor/func/ansi_sequences.py
AthenaColor/models/__init__.py
AthenaColor/models/rgb_controlled.py
AthenaColor/models/rgb_controlled_nested.py
AthenaColor-7.0.2.dist-info/LICENSE
AthenaColor-7.0.2.dist-info/METADATA
AthenaColor-7.0.2.dist-info/WHEEL
AthenaColor-7.0.2.dist-info/top_level.txt
AthenaColor-7.0.2.dist-info/RECORD
